{
    "date": "2026-03-23",
    "left": [
        {
            "code": "002545",
            "name": "东方铁塔",
            "price": 21.59,
            "bias_val": -17.436279852387234,
            "ma20_angle": -37.87776799144879,
            "left_buy_signal": true,
            "right_buy_signal": false,
            "eps": 0.666
        },
        {
            "code": "600141",
            "name": "兴发集团",
            "price": 32.11,
            "bias_val": -16.99517894764053,
            "ma20_angle": -35.98888712017576,
            "left_buy_signal": true,
            "right_buy_signal": false,
            "eps": 1.097
        },
        {
            "code": "600470",
            "name": "六国化工",
            "price": 6.89,
            "bias_val": -13.9932592685058,
            "ma20_angle": 14.389157557229398,
            "left_buy_signal": true,
            "right_buy_signal": false,
            "eps": -0.397
        },
        {
            "code": "002312",
            "name": "川发龙蟒",
            "price": 11.35,
            "bias_val": -11.858352100644568,
            "ma20_angle": -5.53911794067444,
            "left_buy_signal": true,
            "right_buy_signal": false,
            "eps": 0.231
        },
        {
            "code": "000680",
            "name": "山推股份",
            "price": 10.98,
            "bias_val": -11.476599346958524,
            "ma20_angle": -39.60900059648519,
            "left_buy_signal": true,
            "right_buy_signal": false,
            "eps": 0.807
        }
    ],
    "right": [
        {
            "code": "688106",
            "name": "金宏气体",
            "price": 31.0,
            "bias_val": 21.960815170351722,
            "ma20_angle": 61.22212377574806,
            "left_buy_signal": false,
            "right_buy_signal": true,
            "eps": 0.241
        },
        {
            "code": "600617",
            "name": "国新能源",
            "price": 4.15,
            "bias_val": 19.287151480310442,
            "ma20_angle": 58.79452194050299,
            "left_buy_signal": false,
            "right_buy_signal": true,
            "eps": -0.005
        },
        {
            "code": "000968",
            "name": "蓝焰控股",
            "price": 10.68,
            "bias_val": 11.342785654712252,
            "ma20_angle": 56.0710958660401,
            "left_buy_signal": false,
            "right_buy_signal": true,
            "eps": 0.277
        },
        {
            "code": "300080",
            "name": "易成新能",
            "price": 6.31,
            "bias_val": 10.692044557494953,
            "ma20_angle": 49.07471202210119,
            "left_buy_signal": false,
            "right_buy_signal": true,
            "eps": -0.141
        },
        {
            "code": "600982",
            "name": "宁波能源",
            "price": 5.53,
            "bias_val": 8.697788697788695,
            "ma20_angle": 42.68955674922066,
            "left_buy_signal": false,
            "right_buy_signal": true,
            "eps": 0.216
        }
    ]
}